{
  "type_description_msg": {
    "type_description": {
      "type_name": "motor_msgs/msg/EncoderData",
      "fields": [
        {
          "name": "vel_m1",
          "type": {
            "type_id": 6,
            "capacity": 0,
            "string_capacity": 0,
            "nested_type_name": ""
          },
          "default_value": ""
        },
        {
          "name": "dir_m1",
          "type": {
            "type_id": 2,
            "capacity": 0,
            "string_capacity": 0,
            "nested_type_name": ""
          },
          "default_value": ""
        },
        {
          "name": "vel_m2",
          "type": {
            "type_id": 6,
            "capacity": 0,
            "string_capacity": 0,
            "nested_type_name": ""
          },
          "default_value": ""
        },
        {
          "name": "dir_m2",
          "type": {
            "type_id": 2,
            "capacity": 0,
            "string_capacity": 0,
            "nested_type_name": ""
          },
          "default_value": ""
        }
      ]
    },
    "referenced_type_descriptions": []
  },
  "type_hashes": [
    {
      "type_name": "motor_msgs/msg/EncoderData",
      "hash_string": "RIHS01_48598ca816e7e3f5ac10e13045be1a78dce897b5cbdf09e31805f0820e675e36"
    }
  ]
}